sv_geometry/__init__.py
sv_geometry/bidimensional.py
sv_geometry/exception.py
sv_geometry/tridimensional.py
sv_geometry-0.1.3.dist-info/LICENSE
sv_geometry-0.1.3.dist-info/METADATA
sv_geometry-0.1.3.dist-info/WHEEL
sv_geometry-0.1.3.dist-info/top_level.txt
sv_geometry-0.1.3.dist-info/RECORD
