Metadata-Version: 2.1
Name: sv-geometry
Version: 0.1.3
Summary: A collection of functions for bidimensional and tridimensional arithmetic geometry.
Home-page: https://github.com/ihavenonickname/sv-geometry
Author: Gabriel Blank Stift Mousquer
Author-email: gabrielblanksm@gmail.com
License: MIT
Platform: UNKNOWN
